ebir_automation-0.4.0.dist-info/METADATA
ebir_automation-0.4.0.dist-info/WHEEL
ebir_automation-0.4.0.dist-info/licenses/LICENSE
ebir_automation/__init__.py
ebir_automation/ebir_automation.pyd
ebir_automation-0.4.0.dist-info/RECORD
