Metadata-Version: 2.4
Name: ebir-automation
Version: 0.4.0
Classifier: Programming Language :: Python :: 3
Classifier: Programming Language :: Rust
Classifier: Operating System :: Microsoft :: Windows
Classifier: License :: OSI Approved :: MIT License
Classifier: Development Status :: 4 - Beta
Classifier: Intended Audience :: Developers
License-File: LICENSE
Summary: A Python package for automating E-BIR forms
Author-email: noizrom <noizrom@gmail.com>
Requires-Python: >=3.8
Project-URL: Homepage, https://github.com/noizrom/ebir-automation
Project-URL: Source, https://github.com/noizrom/ebir-automation
Project-URL: Issues, https://github.com/noizrom/ebir-automation/issues
